{
  "config": {
    "allowed_ios_versions": ["18.3.0", "18.4", "18.5"]
  },
  "keys": {
    "abcd99": {
      "expires": "2026-04-30",
      "status": "active",
      "note": "Khách A - 30 ngày",
      "allowed_ios_versions": ["18.3.0"]
    },
    "KEYKHACHB-2026": {
      "expires": "2026-07-20",
      "status": "active",
      "note": "Khách B - 6 tháng",
      "allowed_ios_versions": ["18.5"]
    },
    "VIP-999999": {
      "expires": "2026-12-31",
      "status": "active",
      "note": "Khách VIP - 1 năm",
      "allowed_ios_versions": ["18.3.2", "18.4", "18.5"]
    }
  }
}